antlr4_cypher/CypherLexer.py
antlr4_cypher/CypherParser.py
antlr4_cypher/CypherParserListener.py
antlr4_cypher/CypherParserVisitor.py
antlr4_cypher/__init__.py
antlr4_cypher-0.1.2.dist-info/LICENSE
antlr4_cypher-0.1.2.dist-info/METADATA
antlr4_cypher-0.1.2.dist-info/WHEEL
antlr4_cypher-0.1.2.dist-info/top_level.txt
antlr4_cypher-0.1.2.dist-info/RECORD
