Metadata-Version: 2.2
Name: antlr4-cypher
Version: 0.1.2
Summary: A Python package for parsing Cypher queries using ANTLR4.
Home-page: https://github.com/qi-hua/antlr4-cypher
Author: qihua
Author-email: qihua147@qq.com
Classifier: Programming Language :: Python :: 3
Classifier: License :: OSI Approved :: BSD License
Classifier: Operating System :: OS Independent
Requires-Python: >=3.8
License-File: LICENSE
Requires-Dist: antlr4-python3-runtime>=4.9.0
Dynamic: author
Dynamic: author-email
Dynamic: classifier
Dynamic: description
Dynamic: description-content-type
Dynamic: home-page
Dynamic: requires-dist
Dynamic: requires-python
Dynamic: summary
